optimalsolutioncore/__init__.py
optimalsolutioncore/solver.py
optimalsolutioncore/solver_big.py
optimalsolutioncore-0.1.7.dist-info/METADATA
optimalsolutioncore-0.1.7.dist-info/WHEEL
optimalsolutioncore-0.1.7.dist-info/top_level.txt
optimalsolutioncore-0.1.7.dist-info/RECORD
