Metadata-Version: 2.4
Name: optimalsolutioncore
Version: 0.1.7
Summary: Package for solving optimal control problems
Author-email: Ivan Bykov <vanka.perm@mail.ru>
Project-URL: Homepage, https://github.com/mrf0n/OptimalSolutionCore
Classifier: Programming Language :: Python :: 3
Classifier: License :: OSI Approved :: MIT License
Classifier: Operating System :: OS Independent
Requires-Python: >=3.8
Requires-Dist: numpy
Requires-Dist: scipy
Requires-Dist: sympy
Requires-Dist: matplotlib
